livescript/__init__.py
livescript/livescript.js
livescript-1.0.0.dist-info/DESCRIPTION.rst
livescript-1.0.0.dist-info/METADATA
livescript-1.0.0.dist-info/metadata.json
livescript-1.0.0.dist-info/RECORD
livescript-1.0.0.dist-info/top_level.txt
livescript-1.0.0.dist-info/WHEEL
