Metadata-Version: 2.0
Name: livescript
Version: 1.0.0
Summary: Call LiveScript from Python
Home-page: https://github.com/gkovacs/python-livescript
Author: Geza Kovacs
Author-email: geza0kovacs@gmail.com
License: UNKNOWN
Download-URL: https://github.com/gkovacs/python-livescript
Platform: UNKNOWN
Classifier: Development Status :: 3 - Alpha
Classifier: Intended Audience :: Developers
Classifier: Natural Language :: English
Classifier: License :: OSI Approved :: MIT License
Classifier: Programming Language :: Python
Classifier: Programming Language :: Python :: 2
Classifier: Programming Language :: Python :: 2.6
Classifier: Programming Language :: Python :: 2.7
Classifier: Programming Language :: Python :: 3
Classifier: Programming Language :: Python :: 3.1
Classifier: Programming Language :: Python :: 3.2
Classifier: Programming Language :: JavaScript
Requires-Dist: PyExecJS
